weblate_reposync/__init__.py
weblate_reposync-0.1.0.dist-info/LICENSE
weblate_reposync-0.1.0.dist-info/METADATA
weblate_reposync-0.1.0.dist-info/WHEEL
weblate_reposync-0.1.0.dist-info/entry_points.txt
weblate_reposync-0.1.0.dist-info/top_level.txt
weblate_reposync-0.1.0.dist-info/RECORD
