Metadata-Version: 2.1
Name: weblate-reposync
Version: 0.1.0
Summary: Create Weblate translation components based on repository content
Author-email: András Szalai <andrew@bandipapa.com>
License: Copyright (c) 2022, András Szalai
Project-URL: Homepage, https://github.com/bandipapa/weblate_reposync
Requires-Python: >=3.8
License-File: LICENSE
Requires-Dist: GitPython (>=3.1.27)
Requires-Dist: sicopa (>=0.1.0)
